rottencode/__init__.py
rottencode/cli.py
rottencode/code.py
rottencode/events.py
rottencode/logging.py
rottencode/python.py
rottencode/stats.py
rottencode/utils.py
rottencode/cli/__init__.py
rottencode/cli/base.py
rottencode/cli/default.py
rottencode-0.5.1.dist-info/METADATA
rottencode-0.5.1.dist-info/WHEEL
rottencode-0.5.1.dist-info/entry_points.txt
rottencode-0.5.1.dist-info/top_level.txt
rottencode-0.5.1.dist-info/RECORD
